reptor/__init__.py
reptor/__main__.py
reptor/reptorlib.py
reptor/settings.py
reptor/subcommands.py
reptor/title.md
reptor/api/APIClient.py
reptor/api/NotesAPI.py
reptor/api/ProjectDesignsAPI.py
reptor/api/ProjectsAPI.py
reptor/api/TemplatesAPI.py
reptor/api/__init__.py
reptor/api/enums.py
reptor/api/manager.py
reptor/api/tests/__init__.py
reptor/api/tests/test_notes_api.py
reptor/api/tests/test_projects_api.py
reptor/lib/__init__.py
reptor/lib/conf.py
reptor/lib/console.py
reptor/lib/enums.py
reptor/lib/errors.py
reptor/lib/logger.py
reptor/lib/pluginmanager.py
reptor/lib/reptor.py
reptor/lib/importers/BaseImporter.py
reptor/lib/importers/__init__.py
reptor/lib/importers/tests/__init__.py
reptor/lib/importers/tests/test_baseimporter.py
reptor/lib/plugins/Base.py
reptor/lib/plugins/ConfBase.py
reptor/lib/plugins/ModelBase.py
reptor/lib/plugins/PluginMeta.py
reptor/lib/plugins/TestCaseToolPlugin.py
reptor/lib/plugins/ToolBase.py
reptor/lib/plugins/UploadBase.py
reptor/lib/plugins/__init__.py
reptor/lib/plugins/tests/__init__.py
reptor/lib/plugins/tests/test_toolbase.py
reptor/lib/plugins/tests/data/findings/idor.toml
reptor/lib/plugins/tests/data/findings/invalid_finding.toml
reptor/lib/plugins/tests/data/findings/sql.toml
reptor/lib/plugins/tests/data/templates/recommendation.md
reptor/models/Base.py
reptor/models/Finding.py
reptor/models/FindingTemplate.py
reptor/models/Note.py
reptor/models/Project.py
reptor/models/ProjectDesign.py
reptor/models/Section.py
reptor/models/User.py
reptor/models/UserConfig.py
reptor/models/__init__.py
reptor/models/tests/__init__.py
reptor/models/tests/test_note_model.py
reptor/plugins/__init__.py
reptor/plugins/core/__init__.py
reptor/plugins/core/Conf/Conf.py
reptor/plugins/core/Conf/__init__.py
reptor/plugins/core/Conf/tests/__init__.py
reptor/plugins/core/Conf/tests/conftest.py
reptor/plugins/core/Conf/tests/test_dummy.py
reptor/plugins/core/Plugins/Plugins.py
reptor/plugins/importers/DefectDojo/DefectDojo.py
reptor-0.32.dist-info/licenses/LICENSE
reptor-0.32.dist-info/licenses/NOTICE
reptor-0.32.dist-info/METADATA
reptor-0.32.dist-info/WHEEL
reptor-0.32.dist-info/entry_points.txt
reptor-0.32.dist-info/top_level.txt
reptor-0.32.dist-info/RECORD
