Metadata-Version: 2.4
Name: reptor
Version: 0.32
Summary: reptor allows you automating pentest reporting with SysReptor.
Author: Richard Schwabe
Author-email: Aron Molnar <aron@syslifters.com>
Maintainer-email: Syslifters <hello@syslifters.com>
License: Copyright (c) 2023 SysReptor+reptor Developers
Project-URL: Homepage, https://github.com/Syslifters/reptor/blob/main/README.md
Project-URL: Documentation, https://github.com/Syslifters/reptor/blob/main/README.md
Project-URL: Bug Tracker, https://github.com/Syslifters/reptor/issues
Project-URL: Source, https://github.com/syslifters/reptor
Classifier: Programming Language :: Python :: 3
Classifier: Programming Language :: Python :: 3 :: Only
Classifier: Programming Language :: Python :: 3.9
Classifier: Programming Language :: Python :: 3.10
Classifier: Programming Language :: Python :: 3.11
Classifier: Programming Language :: Python :: 3.12
Classifier: License :: OSI Approved :: MIT License
Classifier: Operating System :: OS Independent
Requires-Python: >=3.9
License-File: LICENSE
License-File: NOTICE
Requires-Dist: certifi>=2023.5.7
Requires-Dist: cvss>=3.0
Requires-Dist: Django>=4.2
Requires-Dist: PyYAML>=3.10
Requires-Dist: requests>=2.28.2
Requires-Dist: rich<14,>=10
Requires-Dist: termcolor>=2.3.0
Requires-Dist: urllib3<3,>=1.21.1
Requires-Dist: xmltodict>=0.13
Requires-Dist: tomli<3,>=2.0.1
Requires-Dist: tomli-w>=1.0
Requires-Dist: tomlkit>=0.12.3
Provides-Extra: translate
Requires-Dist: deepl>=1.15.0; extra == "translate"
Provides-Extra: ghostwriter
Requires-Dist: gql[aiohttp]>=3.4.1; extra == "ghostwriter"
Provides-Extra: dev
Requires-Dist: pytest>=7.4.0; extra == "dev"
Provides-Extra: all
Requires-Dist: reptor[dev,ghostwriter,translate]; extra == "all"
Dynamic: license-file
